kt.jsonapi-1.7.0-py3.9-nspkg.pth
kt/jsonapi/__init__.py
kt/jsonapi/api.py
kt/jsonapi/error.py
kt/jsonapi/interfaces.py
kt/jsonapi/link.py
kt/jsonapi/relation.py
kt/jsonapi/serializers.py
kt.jsonapi-1.7.0.dist-info/LICENSE.rst
kt.jsonapi-1.7.0.dist-info/METADATA
kt.jsonapi-1.7.0.dist-info/WHEEL
kt.jsonapi-1.7.0.dist-info/namespace_packages.txt
kt.jsonapi-1.7.0.dist-info/top_level.txt
kt.jsonapi-1.7.0.dist-info/RECORD
