Metadata-Version: 2.1
Name: kt.jsonapi
Version: 1.7.0
Summary: JSON:API support library.
Home-page: https://github.com/keepertech/kt.jsonapi
Author: Fred Drake
Author-email: fred@fdrake.net
Project-URL: Documentation, https://ktjsonapi.readthedocs.io/en/latest/introduction.html
Project-URL: Tracker, https://github.com/keepertech/kt.jsonapi/issues
Classifier: Framework :: Flask
Classifier: Intended Audience :: Developers
Classifier: Operating System :: OS Independent
Classifier: Programming Language :: Python :: 3 :: Only
Classifier: Programming Language :: Python :: 3.7
Classifier: Programming Language :: Python :: 3.8
Classifier: Programming Language :: Python :: 3.9
Classifier: Programming Language :: Python :: 3.10
Classifier: Programming Language :: Python :: 3.11
License-File: LICENSE.rst
Requires-Dist: Flask
Requires-Dist: werkzeug
Requires-Dist: zope.component
Requires-Dist: zope.interface
Requires-Dist: zope.schema
